[
  {
    "idx": 1,
    "type": "notice",
    "title": "2025년 설날 연휴 배송 안내",
    "name": "관리자",
    "id": 1,
    "content": "2025년 설날 연휴로 인해 배송 일정에 차질이 있을 수 있습니다. 연휴 기간 동안 배송이 지연될 수 있으니, 미리 주문을 완료해 주시기 바랍니다. 고객님의 양해 부탁드립니다.",
    "date": "2025-01-15",
    "comment": [
      {
        "cNum": 1,
        "name": "심민수",
        "id": "010-1234-5678",
        "date": "2025-01-18",
        "comment": "공지 감사합니다!"
      },
      {
        "cNum": 2,
        "name": "권원우",
        "id": "010-2345-6789",
        "date": "2025-01-15",
        "comment": "그냥 빨리보내주세요.."
      }
    ]
  },
  {
    "idx": 2,
    "type": "notice",
    "title": "새로운 도서 입고 안내",
    "name": "관리자",
    "id": 1,
    "content": "최신 베스트셀러 및 인기 도서들이 입고되었습니다! 서점 웹사이트에서 새로운 도서를 확인하고 주문해 보세요. 여러분의 독서를 더욱 풍성하게 만들어 드리겠습니다.",
    "date": "2024-12-05",
    "comment": [
      {
        "cNum": 1,
        "name": "서채윤",
        "id": "010-6789-0123",
        "date": "2025-02-22",
        "comment": "좋은 게시물 감사해요. 자주 올게요!"
      },
      {
        "cNum": 2,
        "name": "권원우",
        "id": "010-2345-6789",
        "date": "2025-02-23",
        "comment": "공지 잘 확인했습니다. 도움이 많이 됐어요!"
      },
      {
        "cNum": 3,
        "name": "한상화",
        "id": "010-3456-7890",
        "date": "2025-02-24",
        "comment": "정말 유용한 정보네요. 저장해둡니다!"
      }
    ]
  },
  {
    "idx": 3,
    "type": "notice",
    "title": "온라인 회원가입 시 10% 할인 쿠폰 제공",
    "name": "관리자",
    "id": 1,
    "content": "온라인 회원가입을 하시면 첫 구매 시 사용할 수 있는 10% 할인 쿠폰을 드립니다. 지금 바로 회원가입하고 혜택을 누리세요!",
    "date": "2024-11-20",
    "comment": [
      {
        "cNum": 1,
        "name": "신기연",
        "id": "010-4567-8901",
        "date": "2025-02-25",
        "comment": "새로운 공지 기대하고 있겠습니다!"
      },
      {
        "cNum": 2,
        "name": "백영준",
        "id": "010-5678-9012",
        "date": "2025-02-26",
        "comment": "이 정보 덕분에 고민이 해결됐습니다. 감사합니다!"
      },
      {
        "cNum": 3,
        "name": "허병현",
        "id": "010-8901-2345",
        "date": "2025-02-27",
        "comment": "공지사항 꼼꼼히 읽었어요. 고맙습니다!"
      }
    ]
  },
  {
    "idx": 4,
    "type": "notice",
    "title": "서점 휴무일 안내",
    "name": "관리자",
    "id": 1,
    "content": "서점은 2025년 2월 20일(수) 휴무입니다. 이 날짜에는 고객센터 및 오프라인 매장이 운영되지 않으니 참고하시기 바랍니다. 온라인 주문은 정상적으로 가능하니 많은 이용 부탁드립니다.",
    "date": "2025-02-10",
    "comment": [
      {
        "cNum": 1,
        "name": "신기연",
        "id": "010-4567-8901",
        "date": "2025-02-10",
        "comment": "공지 감사합니다!"
      },
      {
        "cNum": 2,
        "name": "백영준",
        "id": "010-5678-9012",
        "date": "2025-02-20",
        "comment": "그냥 빨리보내주세요.."
      }
    ]
  },
  {
    "idx": 5,
    "type": "notice",
    "title": "모바일 앱 업데이트 안내",
    "name": "관리자",
    "id": 1,
    "content": "서점의 모바일 앱이 최신 버전으로 업데이트되었습니다. 새로운 기능과 개선된 사용자 인터페이스를 확인해 보세요. 앱을 통해 더 빠르고 편리하게 도서를 구매하실 수 있습니다.",
    "date": "2024-10-15",
    "comment": [
      {
        "cNum": 1,
        "name": "노기호",
        "id": "010-9012-3456",
        "date": "2025-02-28",
        "comment": "언제나 좋은 정보 감사합니다. 응원할게요!"
      },
      {
        "cNum": 2,
        "name": "오윤재",
        "id": "010-0123-4567",
        "comment": "책 이벤트 정말 기대되네요. 좋은 소식 감사합니다!"
      }
    ]
  },
  {
    "idx": 6,
    "type": "notice",
    "title": "도서 예약 판매 안내",
    "name": "관리자",
    "id": 1,
    "content": "인기 도서가 예약 판매 중입니다. 예약 판매를 통해 원하는 도서를 미리 확보하세요. 예약 판매 기간 동안만 제공되는 특별 혜택도 놓치지 마세요!",
    "date": "2024-09-10",
    "comment": [
      {
        "cNum": 1,
        "name": "설민선",
        "id": "010-6543-2109",
        "date": "2025-03-02",
        "comment": "늘 공지 올려주셔서 감사해요. 자주 확인 중입니다."
      },
      {
        "cNum": 2,
        "name": "장진아",
        "id": "010-7654-3210",
        "date": "2025-03-03",
        "comment": "유용한 내용 감사합니다. 참고하겠습니다!"
      },
      {
        "cNum": 3,
        "name": "양신영",
        "id": "010-8765-4321",
        "date": "2025-03-04",
        "comment": "이번 공지 내용 정말 중요하네요. 잘 확인했어요!"
      },
      {
        "cNum": 4,
        "name": "제갈해준",
        "id": "010-9876-5432",
        "date": "2025-03-05",
        "comment": "좋은 이벤트 기대하겠습니다. 늘 감사합니다!"
      }
    ]
  },
  {
    "idx": 7,
    "type": "notice",
    "title": "회원 등급 혜택 안내",
    "name": "관리자",
    "id": 1,
    "content": "서점의 회원 등급 제도가 새롭게 개선되었습니다. 등급별 혜택을 확인하시고 더 많은 할인과 특별 이벤트를 누리세요.",
    "date": "2024-08-25",
    "comment": [
      {
        "cNum": 1,
        "name": "허승철",
        "id": "010-0987-6543",
        "date": "2025-03-06",
        "comment": "새로운 소식 기다리고 있었습니다. 고맙습니다!"
      },
      {
        "cNum": 2,
        "name": "최대한",
        "id": "010-4321-9876",
        "date": "2025-03-07",
        "comment": "공지사항 정말 유익했어요. 도움이 됐습니다!"
      },
      {
        "cNum": 3,
        "name": "남궁용호",
        "id": "010-3210-8765",
        "date": "2025-03-08",
        "comment": "이벤트 참여하고 싶어요. 좋은 기회 감사합니다!"
      }
    ]
  },
  {
    "idx": 8,
    "type": "notice",
    "title": "서점 오프라인 매장 운영 시간 변경 안내",
    "name": "관리자",
    "id": 1,
    "content": "서점 오프라인 매장의 운영 시간이 변경되었습니다. 새롭게 조정된 시간을 확인하시고, 방문 계획을 세워 주세요.",
    "date": "2024-07-18",
    "comment": []
  },
  {
    "idx": 9,
    "type": "notice",
    "title": "2025년 봄 시즌 도서 추천",
    "name": "관리자",
    "id": 1,
    "content": "2025년 봄을 맞아 추천 도서 목록을 준비했습니다. 새로운 계절과 함께 읽기 좋은 책들을 소개하니, 봄 시즌 도서들을 만나보세요.",
    "date": "2025-03-05",
    "comment": [
      {
        "cNum": 1,
        "name": "양철수",
        "id": "010-2109-7654",
        "date": "2025-03-09",
        "comment": "좋은 책 정보 덕분에 선택이 쉬워졌습니다!"
      },
      {
        "cNum": 2,
        "name": "손민영",
        "id": "010-1098-6543",
        "date": "2025-03-10",
        "comment": "정말 감사합니다! 좋은 하루 되세요."
      },
      {
        "cNum": 3,
        "name": "사공미주",
        "id": "010-7890-1234",
        "date": "2025-03-11",
        "comment": "내용이 아주 알차네요. 잘 활용하겠습니다!"
      }
    ]
  },
  {
    "idx": 10,
    "type": "notice",
    "title": "도서 가격 인상 안내",
    "name": "관리자",
    "id": 1,
    "content": "최근 출판사에서 가격 인상을 시행함에 따라 일부 도서의 가격이 조정되었습니다. 가격 변동 사항을 확인해 주세요.",
    "date": "2024-06-30",
    "comment": []
  },
  {
    "idx": 11,
    "type": "notice",
    "title": "여름휴가 시즌 배송 지연 안내",
    "name": "관리자",
    "id": 1,
    "content": "여름휴가 시즌으로 인해 배송이 지연될 수 있습니다. 미리 주문해 주시면 빠르게 받아보실 수 있습니다.",
    "date": "2024-07-01",
    "comment": []
  },
  {
    "idx": 12,
    "type": "notice",
    "title": "고객센터 운영 시간 변경 안내",
    "name": "관리자",
    "id": 1,
    "content": "고객센터 운영 시간이 변경되었습니다. 새로운 운영 시간을 참고하시고, 궁금한 점이 있으시면 고객센터로 문의해 주세요.",
    "date": "2024-08-01",
    "comment": []
  },
  {
    "idx": 13,
    "type": "notice",
    "title": "서점 앱 출시 기념 이벤트",
    "name": "관리자",
    "id": 1,
    "content": "서점의 새로운 모바일 앱 출시를 기념하여 특별 이벤트가 진행됩니다. 앱 다운로드 후 참여할 수 있는 다양한 혜택을 확인하세요.",
    "date": "2024-06-10",
    "comment": []
  },
  {
    "idx": 14,
    "type": "notice",
    "title": "추석 연휴 전 배송 마감일 안내",
    "name": "관리자",
    "id": 1,
    "content": "추석 연휴 전 배송이 마감되는 날짜는 2024년 9월 25일입니다. 이 날짜까지 주문을 완료하셔야 연휴 전 배송이 가능합니다.",
    "date": "2024-09-10",
    "comment": []
  },
  {
    "idx": 15,
    "type": "notice",
    "title": "회원 전용 도서 할인 행사",
    "name": "관리자",
    "id": 1,
    "content": "회원님만을 위한 특별 도서 할인 행사를 진행합니다. 회원 가입 후 다양한 할인 혜택을 누리세요!",
    "date": "2024-05-20",
    "comment": []
  },
  {
    "idx": 16,
    "type": "notice",
    "title": "서점 포인트 적립 프로그램 안내",
    "name": "관리자",
    "id": 1,
    "content": "도서를 구매하시면 포인트가 적립됩니다. 적립된 포인트는 향후 구매 시 할인 혜택으로 사용할 수 있습니다. 적립 프로그램을 지금 바로 확인해 보세요.",
    "date": "2024-04-15",
    "comment": []
  },
  {
    "idx": 17,
    "type": "notice",
    "title": "서점 웹사이트 개편 안내",
    "name": "관리자",
    "id": 1,
    "content": "서점 웹사이트가 새롭게 개편되었습니다. 새로운 디자인과 향상된 기능으로 더 나은 쇼핑 경험을 제공합니다.",
    "date": "2024-03-10",
    "comment": []
  },
  {
    "idx": 18,
    "type": "notice",
    "title": "책 선물 서비스 오픈",
    "name": "관리자",
    "id": 1,
    "content": "이제 책을 선물할 수 있는 서비스가 시작되었습니다. 친구나 가족에게 특별한 책 선물을 해보세요.",
    "date": "2024-02-25",
    "comment": []
  },
  {
    "idx": 19,
    "type": "notice",
    "title": "가을 독서 캠페인 참여 안내",
    "name": "관리자",
    "id": 1,
    "content": "가을을 맞아 독서 캠페인이 시작됩니다. 참여하고 다양한 도서 혜택을 얻어 보세요.",
    "date": "2024-09-05",
    "comment": []
  },
  {
    "idx": 20,
    "type": "notice",
    "title": "2024년 겨울맞이 특가 도서 이벤트",
    "name": "관리자",
    "id": 1,
    "content": "2024년 겨울맞이 특가 도서 이벤트가 시작되었습니다. 겨울에 읽기 좋은 책들을 저렴한 가격에 만나보세요.",
    "date": "2024-12-01",
    "comment": []
  },
  {
    "idx": 1,
    "type": "faq",
    "title": "회원가입은 어떻게 하나요?",
    "name": "관리자",
    "id": 1,
    "content": "회원가입은 서점 홈페이지 상단의 '회원가입' 버튼을 클릭하여 진행하실 수 있습니다. 이메일 주소와 비밀번호를 입력한 후, 인증을 완료하면 회원가입이 완료됩니다.",
    "date": "2023-03-15",
    "comment": []
  },
  {
    "idx": 2,
    "type": "faq",
    "title": "비밀번호를 잊어버렸어요. 어떻게 해야 하나요?",
    "name": "관리자",
    "id": 1,
    "content": "비밀번호를 잊으셨다면 로그인 페이지에서 '비밀번호 찾기'를 클릭한 후, 등록된 이메일 주소를 입력하시면 재설정 링크를 보내드립니다.",
    "date": "2023-08-07",
    "comment": []
  },
  {
    "idx": 3,
    "type": "faq",
    "title": "배송 기간은 얼마나 걸리나요?",
    "name": "관리자",
    "id": 1,
    "content": "평균 배송 기간은 결제 완료 후 2~5일 이내입니다. 다만, 연휴나 공휴일에는 배송이 지연될 수 있으니 양해 부탁드립니다.",
    "date": "2022-12-25",
    "comment": []
  },
  {
    "idx": 4,
    "type": "faq",
    "title": "주문한 상품을 취소하려면 어떻게 하나요?",
    "name": "관리자",
    "id": 1,
    "content": "상품이 발송되기 전에만 주문 취소가 가능합니다. '마이페이지 > 주문 내역'에서 취소를 원하는 주문을 선택하고 '취소 요청' 버튼을 눌러주세요.",
    "date": "2023-05-19",
    "comment": []
  },
  {
    "idx": 5,
    "type": "faq",
    "title": "교환 및 반품은 어떻게 하나요?",
    "name": "관리자",
    "id": 1,
    "content": "상품 수령 후 7일 이내에 교환 및 반품 요청이 가능합니다. 단, 도서의 경우 비닐 포장이 훼손되지 않은 상태여야 하며, 자세한 사항은 고객센터로 문의해 주세요.",
    "date": "2024-01-12",
    "comment": []
  },
  {
    "idx": 6,
    "type": "faq",
    "title": "적립된 포인트는 어떻게 사용하나요?",
    "name": "관리자",
    "id": 1,
    "content": "포인트는 결제 시 '포인트 사용' 옵션을 선택하여 사용할 수 있습니다. 일부 상품에는 포인트 사용이 제한될 수 있습니다.",
    "date": "2024-07-22",
    "comment": []
  },
  {
    "idx": 7,
    "type": "faq",
    "title": "현금영수증 발급은 어떻게 신청하나요?",
    "name": "관리자",
    "id": 1,
    "content": "주문 시 결제 단계에서 '현금영수증 발급'을 선택하거나, 결제 완료 후 '마이페이지 > 주문 내역'에서 현금영수증 발급 신청이 가능합니다.",
    "date": "2022-11-10",
    "comment": []
  },
  {
    "idx": 8,
    "type": "faq",
    "title": "서점에서 제공하는 배송비 정책은 무엇인가요?",
    "name": "관리자",
    "id": 1,
    "content": "총 주문 금액이 30,000원 이상일 경우 무료 배송 혜택이 제공됩니다. 30,000원 미만 주문 시 배송비 3,000원이 부과됩니다.",
    "date": "2023-06-14",
    "comment": []
  },
  {
    "idx": 9,
    "type": "faq",
    "title": "예약 판매 상품은 언제 배송되나요?",
    "name": "관리자",
    "id": 1,
    "content": "예약 판매 상품은 공식 출간일 이후 순차적으로 배송됩니다. 배송 일정은 상품 페이지에서 확인 가능합니다.",
    "date": "2024-03-05",
    "comment": []
  },
  {
    "idx": 10,
    "type": "faq",
    "title": "오프라인 매장에서도 같은 혜택을 받을 수 있나요?",
    "name": "관리자",
    "id": 1,
    "content": "오프라인 매장과 온라인 서점의 할인 및 이벤트는 일부 상이할 수 있습니다. 오프라인 매장의 혜택은 방문 전에 매장 직원에게 문의해 주세요.",
    "date": "2023-09-30",
    "comment": []
  },
  {
    "idx": 11,
    "type": "faq",
    "title": "회원가입 시 어떤 정보를 입력해야 하나요?",
    "name": "관리자",
    "id": 1,
    "content": "회원가입 시 이름, 이메일, 비밀번호를 입력하셔야 하며, 선택적으로 연락처를 등록하실 수 있습니다.",
    "date": "2023-07-12",
    "comment": []
  },
  {
    "idx": 12,
    "type": "faq",
    "title": "서점 포인트는 어떻게 적립되나요?",
    "name": "관리자",
    "id": 1,
    "content": "서점 포인트는 상품 구매 시 자동으로 적립됩니다. 적립률은 상품마다 다를 수 있으니 확인 부탁드립니다.",
    "date": "2023-08-15",
    "comment": []
  },
  {
    "idx": 13,
    "type": "faq",
    "title": "구매한 책이 파손되어 왔습니다. 어떻게 해야 하나요?",
    "name": "관리자",
    "id": 1,
    "content": "파손된 책을 받으셨다면, 배송 후 7일 이내에 고객센터로 문의 주시면 교환 처리해 드리겠습니다.",
    "date": "2024-01-10",
    "comment": []
  },
  {
    "idx": 14,
    "type": "faq",
    "title": "전자책을 구매하면 다운로드는 어떻게 하나요?",
    "name": "관리자",
    "id": 1,
    "content": "전자책은 구매 후 '내 서재'에서 확인 및 다운로드 가능합니다. 다운로드 시 전용 리더 앱이 필요할 수 있습니다.",
    "date": "2023-10-03",
    "comment": []
  },
  {
    "idx": 15,
    "type": "faq",
    "title": "1회 주문 시 최대 몇 권까지 구매할 수 있나요?",
    "name": "관리자",
    "id": 1,
    "content": "1회 주문 시 최대 20권까지 구매 가능하며, 그 이상 주문을 원하실 경우 고객센터로 문의해 주세요.",
    "date": "2022-12-20",
    "comment": []
  },
  {
    "idx": 16,
    "type": "faq",
    "title": "주문 후 배송지를 변경할 수 있나요?",
    "name": "관리자",
    "id": 1,
    "content": "배송지 변경은 배송 시작 전까지 가능합니다. 마이페이지에서 변경하거나 고객센터로 요청해 주세요.",
    "date": "2023-06-08",
    "comment": []
  },
  {
    "idx": 17,
    "type": "faq",
    "title": "정기구독 서비스를 제공하나요?",
    "name": "관리자",
    "id": 1,
    "content": "현재 정기구독 서비스는 제공되지 않으나, 관련 서비스 도입을 검토 중입니다.",
    "date": "2024-03-04",
    "comment": []
  },
  {
    "idx": 18,
    "type": "faq",
    "title": "구매 내역은 어디에서 확인할 수 있나요?",
    "name": "관리자",
    "id": 1,
    "content": "구매 내역은 로그인 후 '마이페이지 > 구매 내역'에서 확인하실 수 있습니다.",
    "date": "2023-11-16",
    "comment": []
  },
  {
    "idx": 19,
    "type": "faq",
    "title": "서점에서 제공하는 선물 포장 서비스가 있나요?",
    "name": "관리자",
    "id": 1,
    "content": "현재 선물 포장 서비스는 제공되지 않으나, 요청 시 간단한 포장 옵션을 선택할 수 있습니다.",
    "date": "2023-04-09",
    "comment": []
  },
  {
    "idx": 20,
    "type": "faq",
    "title": "상품 후기는 어디에 남길 수 있나요?",
    "name": "관리자",
    "id": 1,
    "content": "구매하신 상품의 후기는 '마이페이지 > 구매 내역'에서 해당 상품을 선택한 후 작성하실 수 있습니다.",
    "date": "2024-02-17",
    "comment": []
  },
  {
    "idx": 1,
    "type": "freeboard",
    "image": "img-996133762",
    "title": "요즘 읽고 있는 책 추천해요!",
    "name": "서채윤",
    "id": "010-6789-0123",
    "content": "최근에 읽은 책 중 '모모'라는 책이 정말 인상 깊었습니다. 시간의 소중함과 삶의 본질에 대해 생각하게 되는 책이에요. 특히 이야기 속의 캐릭터들이 너무 매력적이고, 저를 깊이 몰입하게 했어요. 요즘 바쁘게 살면서 스스로에게 너무 엄격했던 것 같은데, 이 책을 읽으면서 많은 위로를 받았습니다. 여러분께도 추천드려요!",
    "date": "2023-03-11",
    "comment": [
      {
        "cNum": 1,
        "name": "손민영",
        "id": "010-1098-6543",
        "date": "2025-02-18",
        "comment": "다음에도 좋은 소식 기대할게요!"
      },
      {
        "cNum": 2,
        "name": "사공미주",
        "id": "010-7890-1234",
        "date": "2025-02-19",
        "comment": "이벤트 당첨되길 바라봅니다. 감사합니다!"
      },
      {
        "cNum": 3,
        "name": "추성희",
        "id": "010-5432-1098",
        "date": "2025-02-20",
        "comment": "정말 유용한 정보예요. 공유 감사합니다!"
      },
      {
        "cNum": 4,
        "name": "심민수",
        "id": "010-1234-5678",
        "date": "2025-02-21",
        "comment": "책 관련된 정보는 항상 환영입니다!"
      }
    ]
  },
  {
    "idx": 2,
    "type": "freeboard",
    "image": "img-996370966",
    "title": "이벤트 상품 도착했어요!",
    "name": "추성희",
    "id": "010-5432-1098",
    "content": "서점 이벤트로 참여했던 상품이 드디어 도착했어요! 너무 기대하고 있었는데 포장도 깔끔하고 책 상태도 정말 완벽해서 대만족입니다. 특히 제가 좋아하는 작가의 신작이라서 더 설렜던 것 같아요. 앞으로도 이런 이벤트가 자주 열렸으면 좋겠어요. 다른 분들은 어떤 상품을 받으셨는지 궁금하네요!",
    "date": "2022-12-24",
    "comment": [
      {
        "cNum": 1,
        "name": "최대한",
        "id": "010-4321-9876",
        "date": "2025-02-15",
        "comment": "어떤 책을 먼저 읽어야 할지 고민되네요!"
      },
      {
        "cNum": 2,
        "name": "남궁용호",
        "id": "010-3210-8765",
        "date": "2025-02-16",
        "comment": "이 글 덕분에 새로운 책을 알게 되었어요!"
      },
      {
        "cNum": 3,
        "name": "양철수",
        "id": "010-2109-7654",
        "date": "2025-02-17",
        "comment": "언제나 신뢰할 수 있는 정보, 감사합니다!"
      }
    ]
  },
  {
    "idx": 3,
    "type": "freeboard",
    "image": "img-996515641",
    "title": "전자책과 종이책, 뭐가 더 좋으세요?",
    "name": "최대한",
    "id": "010-4321-9876",
    "content": "요즘 전자책 리더기를 구매하려고 고민 중인데요, 종이책만의 감성이 그리울 것 같아서 망설여집니다. 전자책은 언제 어디서나 편리하게 읽을 수 있어서 좋을 것 같고, 종이책은 손으로 넘기는 느낌과 책장에 꽂아두는 기쁨이 있잖아요. 여러분은 어떤 방식으로 독서를 즐기고 계신지 궁금합니다. 의견 나눠주세요!",
    "date": "2024-02-15",
    "comment": [
      {
        "cNum": 1,
        "name": "제갈해준",
        "id": "010-9876-5432",
        "date": "2025-02-13",
        "comment": "이번 이벤트도 꼭 참여할게요. 기대됩니다!"
      },
      {
        "cNum": 2,
        "name": "허승철",
        "id": "010-0987-6543",
        "date": "2025-02-14",
        "comment": "공지사항 항상 잘 보고 있습니다. 감사합니다."
      }
    ]
  },
  {
    "idx": 4,
    "type": "freeboard",
    "image": "img-996918794",
    "title": "책 읽는 습관 어떻게 들이세요?",
    "name": "백영준",
    "id": "010-5678-9012",
    "content": "책을 꾸준히 읽는 습관을 들이는 게 정말 어렵네요. 처음엔 의욕이 넘쳤는데 시간이 지날수록 핸드폰에 손이 가요. 하루에 30분씩이라도 정해진 시간에 책을 읽으려고 하는데도 쉽지 않네요. 혹시 여러분은 어떤 방식으로 독서를 꾸준히 하시나요? 특별한 노하우나 팁이 있으면 공유 부탁드릴게요.",
    "date": "2023-07-21",
    "comment": [
      {
        "cNum": 1,
        "name": "설민선",
        "id": "010-6543-2109",
        "date": "2025-02-10",
        "comment": "정말 공지 기다렸어요. 감사합니다!"
      },
      {
        "cNum": 2,
        "name": "장진아",
        "id": "010-7654-3210",
        "date": "2025-02-11",
        "comment": "다음번엔 조금 더 빨리 공지 부탁드립니다."
      },
      {
        "cNum": 3,
        "name": "양신영",
        "id": "010-8765-4321",
        "date": "2025-02-12",
        "comment": "꼼꼼한 설명 감사합니다. 잘 읽었습니다!"
      }
    ]
  },
  {
    "idx": 5,
    "type": "freeboard",
    "image": "img-997218055",
    "title": "인생 책 하나만 추천해주세요!",
    "name": "장진아",
    "id": "010-7654-3210",
    "content": "살면서 가장 감명 깊게 읽었던 책을 한 권만 추천해 주세요! 저는 '어린 왕자'를 인생 책으로 꼽고 싶어요. 읽을 때마다 새로운 메시지를 발견하고 마음에 울림을 주는 책이더라고요. 여러분에게도 그런 책이 있다면 추천 부탁드립니다. 다양한 책들을 알게 되면 좋겠어요!",
    "date": "2022-11-08",
    "comment": [
      {
        "cNum": 1,
        "name": "노기호",
        "id": "010-9012-3456",
        "date": "2025-02-08",
        "comment": "자세한 설명 감사드립니다. 많은 도움이 되었습니다."
      },
      {
        "cNum": 2,
        "name": "오윤재",
        "id": "010-0123-4567",
        "comment": "이거 진짜 좋은 정보네요. 저장해둘게요!"
      }
    ]
  },
  {
    "idx": 6,
    "type": "freeboard",
    "image": "img-997458333",
    "title": "독서 모임 만들고 싶어요!",
    "name": "허승철",
    "id": "010-0987-6543",
    "content": "책을 좋아하는 분들과 함께 이야기를 나눌 수 있는 독서 모임을 만들고 싶어요. 책에 대한 다양한 관점과 해석을 공유하면서 더 깊은 독서를 즐길 수 있을 것 같아요. 관심 있는 분들은 댓글로 알려주세요. 모임을 만들 때 참고할 만한 조언도 해주시면 감사하겠습니다!",
    "date": "2024-01-12",
    "comment": [
      {
        "cNum": 1,
        "name": "백영준",
        "id": "010-5678-9012",
        "date": "2025-02-06",
        "comment": "빠른 답변 부탁드립니다."
      },
      {
        "cNum": 2,
        "name": "허병현",
        "id": "010-8901-2345",
        "date": "2025-02-07",
        "comment": "정말 공감되는 내용이에요. 글 잘 읽었습니다."
      }
    ]
  },
  {
    "idx": 7,
    "type": "freeboard",
    "image": "img-997650292",
    "title": "출판사 이름 궁금해요",
    "name": "심민수",
    "id": "010-1234-5678",

    "content": "추리 소설을 전문적으로 다루는 출판사를 알고 싶습니다. 최근 추리 소설에 푹 빠져 있는데, 다양한 책을 찾아보고 싶어요. 혹시 추천할 만한 출판사가 있다면 알려주세요. 명작부터 신작까지 골고루 읽어보고 싶습니다. 여러분의 의견을 기다릴게요!",
    "date": "2023-09-05"
  },
  {
    "idx": 8,
    "type": "freeboard",
    "image": "img-998278024",
    "title": "책 읽는 장소 추천 부탁드려요",
    "name": "사공미주",
    "id": "010-7890-1234",
    "content": "조용히 책을 읽기 좋은 장소를 찾고 있어요. 집에서는 자꾸 딴짓을 하게 되고, 카페는 시끄러워서 집중이 안 돼요. 공원이나 도서관처럼 좋은 장소를 알고 계신 분들, 추천 부탁드립니다. 여러분이 가장 좋아하는 독서 장소는 어디인가요?",
    "date": "2023-06-12",
    "comment": [
      {
        "cNum": 1,
        "name": "권원우",
        "id": "010-2345-6789",
        "date": "2025-02-03",
        "comment": "이벤트 언제 다시 진행하나요? 기다리고 있습니다!"
      },
      {
        "cNum": 2,
        "name": "한상화",
        "id": "010-3456-7890",
        "date": "2025-02-04",
        "comment": "책 추천 너무 좋네요. 꼭 읽어볼게요!"
      },
      {
        "cNum": 3,
        "name": "신기연",
        "id": "010-4567-8901",
        "date": "2025-02-05",
        "comment": "확인했습니다. 좋은 하루 보내세요!"
      }
    ]
  },
  {
    "idx": 9,
    "type": "freeboard",
    "image": "img-998349075",
    "title": "작가 인터뷰 읽는 재미!",
    "name": "허병현",
    "id": "010-8901-2345",
    "content": "최근 읽은 책의 작가 인터뷰를 보니, 작품의 배경과 영감이 어디서 왔는지 알게 되어 흥미로웠어요. 작가의 시각으로 작품을 이해하니 더 깊이 읽히는 것 같아요. 여러분도 재미있게 본 인터뷰가 있으면 공유해주세요. 새로운 작품을 발견하는 데 큰 도움이 될 것 같아요!",
    "date": "2023-02-20",
    "comment": [
      {
        "cNum": 1,
        "name": "심민수",
        "id": "010-1234-5678",
        "date": "2025-02-01",
        "comment": "좋은 정보 감사합니다! 유용하게 활용할게요."
      },
      {
        "cNum": 2,
        "name": "서채윤",
        "id": "010-6789-0123",
        "date": "2025-02-02",
        "comment": "정말 유익한 내용이네요. 공유 감사합니다!"
      }
    ]
  },
  {
    "idx": 10,
    "type": "freeboard",
    "image": "img-998366957",
    "title": "도서 정리 방법 공유해요",
    "name": "손민영",
    "id": "010-1098-6543",
    "content": "책장이 점점 가득 차면서 어떻게 정리해야 할지 고민입니다. 장르별로 나눌지, 작가 이름 순으로 정리할지 아직도 헷갈려요. 효율적이면서도 보기 좋은 도서 정리법이 있다면 알려주세요. 여러분은 어떻게 책장을 꾸미고 계신가요? 사진도 함께 공유해주세요!",
    "date": "2024-03-09",
    "comment": []
  },
  {
    "idx": 11,
    "type": "freeboard",
    "image": "img-998576188",
    "title": "어린이 책 추천 부탁드립니다!",
    "name": "노기호",
    "id": "010-9012-3456",
    "content": "조카에게 생일 선물로 줄 만한 어린이 책을 찾고 있습니다. 주로 초등학교 저학년 아이가 재미있게 읽을 수 있는 책을 추천받고 싶어요. 교훈도 있으면서 흥미로운 이야기라면 더 좋을 것 같아요. 혹시 기억에 남는 책이나 인기가 많은 책이 있다면 알려주세요!",
    "date": "2023-08-04",
    "comment": []
  },
  {
    "idx": 12,
    "type": "freeboard",
    "image": "img-998637718",
    "title": "책 표지 디자인에 대한 이야기",
    "name": "양철수",
    "id": "010-2109-7654",
    "content": "책을 구매할 때 표지 디자인이 정말 큰 영향을 미치는 것 같아요. 예쁜 표지의 책은 왠지 더 읽고 싶어지는 매력이 있더라고요. 여러분도 책 표지를 보고 구매한 경험이 있나요? 기억에 남는 디자인이나 인상 깊었던 표지가 있으면 공유 부탁드려요!",
    "date": "2023-12-19",
    "comment": []
  },
  {
    "idx": 13,
    "type": "freeboard",
    "image": "img-998857615",
    "title": "번역본 vs 원서, 어떤 걸 선호하시나요?",
    "name": "제갈해준",
    "id": "010-9876-5432",
    "content": "외국 서적을 읽을 때 번역본과 원서 중 어떤 것을 더 선호하시나요? 번역본은 이해가 쉽고, 원서는 원작의 뉘앙스를 더 잘 느낄 수 있는 것 같아요. 여러분은 어떤 기준으로 선택하시는지 궁금합니다. 추천할 만한 원서도 함께 알려주세요!",
    "date": "2024-01-07",
    "comment": []
  },
  {
    "idx": 14,
    "type": "freeboard",
    "image": "img-998995026",
    "title": "책 속 문구, 가장 기억에 남는 것은?",
    "name": "오윤재",
    "id": "010-0123-4567",
    "content": "책을 읽다가 가슴에 와닿는 문장을 발견할 때 정말 기쁩니다. 여러분은 지금까지 읽었던 책 중에서 가장 기억에 남는 문구가 무엇인가요? 저는 '어린 왕자'의 '가장 중요한 것은 눈에 보이지 않는다'라는 문구가 항상 마음에 남아있어요.",
    "date": "2023-05-22",
    "comment": []
  },
  {
    "idx": 15,
    "type": "freeboard",
    "image": "img-9961234799",
    "title": "연말 독서 계획 세우기",
    "name": "허병현",
    "id": "010-8901-2345",
    "content": "어느덧 연말이 다가오고 있네요. 올 한 해 동안 읽고 싶었던 책 중에서 못 읽은 책들을 마저 읽으려고 계획 중입니다. 여러분도 연말 독서 계획을 세우셨나요? 어떤 책을 읽을 예정인지 공유해 주시면 저도 참고해서 리스트에 추가하고 싶습니다!",
    "date": "2023-11-30",
    "comment": []
  },
  {
    "idx": 16,
    "type": "freeboard",
    "image": "img-9961850403",
    "title": "독서와 필사의 조합, 해보셨나요?",
    "name": "신기연",
    "id": "010-4567-8901",
    "content": "요즘 독서를 하면서 좋은 문장을 필사하는 습관을 들이고 있어요. 필사를 하면 문장이 더 깊이 새겨지고 기억에 오래 남는 것 같아요. 여러분도 필사를 해보신 적 있나요? 추천할 만한 문장이나 책이 있으면 알려주세요. 같이 공유해봐요!",
    "date": "2024-02-09",
    "comment": []
  },
  {
    "idx": 17,
    "type": "freeboard",
    "image": "img-9961995350",
    "title": "서점에서 책 고르는 팁",
    "name": "심민수",
    "id": "010-1234-5678",

    "content": "서점에 가면 수많은 책들 중에서 무엇을 고를지 항상 고민됩니다. 제가 주로 활용하는 방법은 책의 첫 몇 페이지를 읽어보는 것인데요. 여러분은 어떤 기준으로 책을 선택하시나요? 추천 팁이나 고르는 노하우가 있다면 알려주세요!",
    "date": "2023-03-25",
    "comment": []
  },
  {
    "idx": 18,
    "type": "freeboard",
    "image": "img-9962318222",
    "title": "책과 함께 떠나는 여행",
    "name": "남궁용호",
    "id": "010-3210-8765",
    "content": "여행 갈 때 꼭 책을 챙기는 편인데, 휴식 시간에 읽으면 정말 좋더라고요. 특히 여행지와 관련된 책을 읽으면 몰입감이 배가되는 것 같아요. 여러분은 여행하면서 읽기 좋은 책으로 어떤 걸 추천하시나요? 특별한 경험이 있으면 나눠주세요!",
    "date": "2023-07-14",
    "comment": []
  },
  {
    "idx": 19,
    "type": "freeboard",
    "image": "img-9962367184",
    "title": "중고책 거래, 믿을 수 있을까요?",
    "name": "설민선",
    "id": "010-6543-2109",
    "content": "중고책을 구매해본 경험이 거의 없어서 고민입니다. 상태가 괜찮은 책을 구매하고 싶은데, 믿을 수 있는 플랫폼이나 판매자를 어떻게 확인해야 할까요? 중고책 거래 경험이 있으신 분들의 조언을 듣고 싶습니다. 추천도 부탁드려요!",
    "date": "2023-10-02",
    "comment": []
  },
  {
    "idx": 20,
    "type": "freeboard",
    "image": "img-9962372328",
    "title": "책에 대한 리뷰는 어디서 보시나요?",
    "name": "한상화",
    "id": "010-3456-7890",
    "content": "책을 구매하기 전에 리뷰를 꼭 찾아보는 편인데, 어디에서 가장 신뢰할 만한 리뷰를 볼 수 있을까요? 저는 주로 서점 사이트나 블로그에서 찾는 편이에요. 여러분은 책 리뷰를 어디서 확인하시나요? 추천할 만한 사이트나 채널이 있다면 알려주세요!",
    "date": "2023-01-18",
    "comment": []
  }
]
